odoo10_addon_l10n_es_dua-10.0.1.0.0-py2.7-nspkg.pth
odoo/addons/l10n_es_dua/README.rst
odoo/addons/l10n_es_dua/__init__.py
odoo/addons/l10n_es_dua/__manifest__.py
odoo/addons/l10n_es_dua/data/fiscal_position_taxes_dua.xml
odoo/addons/l10n_es_dua/data/fiscal_positions_dua.xml
odoo/addons/l10n_es_dua/data/products_dua.xml
odoo/addons/l10n_es_dua/data/taxes_dua.xml
odoo/addons/l10n_es_dua/static/description/icon.png
odoo10_addon_l10n_es_dua-10.0.1.0.0.dist-info/DESCRIPTION.rst
odoo10_addon_l10n_es_dua-10.0.1.0.0.dist-info/METADATA
odoo10_addon_l10n_es_dua-10.0.1.0.0.dist-info/RECORD
odoo10_addon_l10n_es_dua-10.0.1.0.0.dist-info/WHEEL
odoo10_addon_l10n_es_dua-10.0.1.0.0.dist-info/metadata.json
odoo10_addon_l10n_es_dua-10.0.1.0.0.dist-info/namespace_packages.txt
odoo10_addon_l10n_es_dua-10.0.1.0.0.dist-info/top_level.txt
